my_rabbitmq_package/__init__.py
my_rabbitmq_package/consumer.py
my_rabbitmq_package/publisher.py
my_rabbitmq_package-0.1.4.dist-info/METADATA
my_rabbitmq_package-0.1.4.dist-info/WHEEL
my_rabbitmq_package-0.1.4.dist-info/top_level.txt
my_rabbitmq_package-0.1.4.dist-info/RECORD
