Metadata-Version: 2.1
Name: my_rabbitmq_package
Version: 0.1.4
Summary: A Python package for RabbitMQ interactions
Home-page: https://github.com/anshulchaintha/rabbitmqpractice
Author: Anshul Chaintha
Author-email: anshulchaintha7@gmail.com
Classifier: Programming Language :: Python :: 3
Classifier: License :: OSI Approved :: MIT License
Classifier: Operating System :: OS Independent
Requires-Python: >=3.6
Requires-Dist: pika
